llm_groq_whisper.py
llm_groq_whisper-0.1a0.dist-info/LICENSE
llm_groq_whisper-0.1a0.dist-info/METADATA
llm_groq_whisper-0.1a0.dist-info/WHEEL
llm_groq_whisper-0.1a0.dist-info/entry_points.txt
llm_groq_whisper-0.1a0.dist-info/top_level.txt
llm_groq_whisper-0.1a0.dist-info/RECORD
