Metadata-Version: 2.1
Name: llm-groq-whisper
Version: 0.1a0
Summary: Transcribe audio using the Groq.com Whisper API
Author: Simon Willison
License: Apache-2.0
Project-URL: Homepage, https://github.com/simonw/llm-groq-whisper
Project-URL: Changelog, https://github.com/simonw/llm-groq-whisper/releases
Project-URL: Issues, https://github.com/simonw/llm-groq-whisper/issues
Project-URL: CI, https://github.com/simonw/llm-groq-whisper/actions
Classifier: License :: OSI Approved :: Apache Software License
Requires-Python: >=3.9
License-File: LICENSE
Requires-Dist: llm
Provides-Extra: test
Requires-Dist: pytest ; extra == 'test'
Requires-Dist: cogapp ; extra == 'test'
